atsas/__init__.py
atsas/atsas_logo.gif
atsas/bibtex.py
atsas/constants.py
atsas/protocols.conf
atsas/protocols/__init__.py
atsas/protocols/protocol_pdb_to_saxs.py
atsas/viewers/__init__.py
atsas/viewers/viewer.py
scipion_em_atsas-3.1.dist-info/LICENSE
scipion_em_atsas-3.1.dist-info/METADATA
scipion_em_atsas-3.1.dist-info/WHEEL
scipion_em_atsas-3.1.dist-info/entry_points.txt
scipion_em_atsas-3.1.dist-info/top_level.txt
scipion_em_atsas-3.1.dist-info/RECORD
